broadcastify_cli/__init__.py
broadcastify_cli/broadcastify_cli.py
broadcastify_cli-0.1.2.dist-info/LICENSE
broadcastify_cli-0.1.2.dist-info/METADATA
broadcastify_cli-0.1.2.dist-info/WHEEL
broadcastify_cli-0.1.2.dist-info/entry_points.txt
broadcastify_cli-0.1.2.dist-info/top_level.txt
broadcastify_cli-0.1.2.dist-info/RECORD
