Metadata-Version: 2.1
Name: broadcastify-cli
Version: 0.1.2
Summary: CLI for interacting with the unoffical broadcastify API
Author-email: NotJoeMartinez <notjoemartinez@protonmail.com>
License: GNU GENERAL PUBLIC LICENSE 
Project-URL: Homepage, https://github.com/NotJoeMartinez/broadcastify-cli
Keywords: radio,cli,broadcastify
Classifier: License :: OSI Approved :: GNU General Public License v3 or later (GPLv3+)
Classifier: Programming Language :: Python :: 3
Classifier: Operating System :: OS Independent
Requires-Python: >=3.8
License-File: LICENSE
Requires-Dist: certifi ==2024.2.2
Requires-Dist: charset-normalizer ==3.3.2
Requires-Dist: click ==8.1.7
Requires-Dist: idna ==3.7
Requires-Dist: markdown-it-py ==3.0.0
Requires-Dist: mdurl ==0.1.2
Requires-Dist: Pygments ==2.17.2
Requires-Dist: python-dotenv ==1.0.1
Requires-Dist: requests ==2.31.0
Requires-Dist: rich ==13.7.1
Requires-Dist: urllib3 ==2.2.1
Requires-Dist: pydub ==0.25.1
Requires-Dist: openai ==1.22.0
Requires-Dist: faster-whisper ==1.0.1
